json_agent/__init__.py
gemini_json_agent-0.0.1.dist-info/LICENSE
gemini_json_agent-0.0.1.dist-info/METADATA
gemini_json_agent-0.0.1.dist-info/WHEEL
gemini_json_agent-0.0.1.dist-info/top_level.txt
gemini_json_agent-0.0.1.dist-info/RECORD
