Metadata-Version: 2.1
Name: gemini-json-agent
Version: 0.0.1
Summary: Agent For Working With JSON Data Structure
Author: Viacheslav Kovalevskyi
Author-email: viacheslav@kovalevskyi.com
License: MIT
License-File: LICENSE
Requires-Dist: gemini-agents-toolkit==2.*
